cli/__init__.py
llama_cli/__init__.py
llama_cli/config.py
llama_cli/interactive.py
llama_cli/main.py
llama_cli/commands/__init__.py
llama_cli/commands/analytics.py
llama_cli/commands/api.py
llama_cli/commands/auth.py
llama_cli/commands/config.py
llama_cli/commands/db.py
llama_cli/commands/kv.py
llama_cli/commands/pdf.py
llama_cli/commands/plugins.py
llama_cli/commands/search.py
llama_cli/commands/shell.py
llama_cli/utils/__init__.py
llama_cli/utils/output.py
llama_cli_llamasearch-0.1.0.dist-info/licenses/LICENSE
llama_cli_llamasearch-0.1.0.dist-info/METADATA
llama_cli_llamasearch-0.1.0.dist-info/WHEEL
llama_cli_llamasearch-0.1.0.dist-info/entry_points.txt
llama_cli_llamasearch-0.1.0.dist-info/top_level.txt
llama_cli_llamasearch-0.1.0.dist-info/RECORD
