Metadata-Version: 2.4
Name: llama-cli-llamasearch
Version: 0.1.0
Summary: Command-line interface for LlamaSearch.ai tools
Home-page: https://llamasearch.ai
Author: LlamaSearch AI
Author-email: nikjois@llamasearch.ai
Project-URL: Bug Tracker, https://github.com/llamasearch/llama-cli/issues
Project-URL: Documentation, https://docs.llamasearch.ai/llama-cli
Classifier: Programming Language :: Python :: 3
Classifier: Programming Language :: Python :: 3.8
Classifier: Programming Language :: Python :: 3.9
Classifier: Programming Language :: Python :: 3.10
Classifier: Programming Language :: Python :: 3.11
Classifier: License :: OSI Approved :: MIT License
Classifier: Operating System :: OS Independent
Classifier: Development Status :: 4 - Beta
Classifier: Intended Audience :: Developers
Classifier: Topic :: Software Development :: Libraries :: Python Modules
Classifier: Topic :: Utilities
Requires-Python: >=3.8
License-File: LICENSE
Requires-Dist: click>=8.0.0
Requires-Dist: pyyaml>=6.0
Requires-Dist: requests>=2.25.0
Requires-Dist: rich>=10.0.0
Requires-Dist: typer>=0.4.0
Requires-Dist: pydantic>=1.8.0
Requires-Dist: tabulate>=0.8.9
Requires-Dist: prompt-toolkit>=3.0.0
Requires-Dist: PyInquirer>=1.0.3
Requires-Dist: colorama>=0.4.4
Requires-Dist: keyring>=23.0.0
Provides-Extra: dev
Requires-Dist: pytest>=6.0.0; extra == "dev"
Requires-Dist: pytest-cov>=2.12.0; extra == "dev"
Requires-Dist: black>=21.5b2; extra == "dev"
Requires-Dist: flake8>=3.9.2; extra == "dev"
Requires-Dist: mypy>=0.812; extra == "dev"
Requires-Dist: isort>=5.9.1; extra == "dev"
Requires-Dist: tox>=3.24.0; extra == "dev"
Provides-Extra: docs
Requires-Dist: sphinx>=4.0.2; extra == "docs"
Requires-Dist: sphinx-rtd-theme>=0.5.2; extra == "docs"
Requires-Dist: sphinx-click>=3.0.0; extra == "docs"
Dynamic: author
Dynamic: author-email
Dynamic: classifier
Dynamic: description
Dynamic: description-content-type
Dynamic: home-page
Dynamic: license-file
Dynamic: project-url
Dynamic: provides-extra
Dynamic: requires-dist
Dynamic: requires-python
Dynamic: summary
